bw_menu/__init__.py
bw_menu/__main__.py
bw_menu/vault/__init__.py
bw_menu-0.1.1.data/scripts/bw-menu
tkinter/__init__.py
tkinter/simpledialog/__init__.py
bw_menu-0.1.1.dist-info/LICENSE
bw_menu-0.1.1.dist-info/METADATA
bw_menu-0.1.1.dist-info/WHEEL
bw_menu-0.1.1.dist-info/top_level.txt
bw_menu-0.1.1.dist-info/RECORD
