Metadata-Version: 2.1
Name: bw-menu
Version: 0.1.1
Summary: Pop-up BitWarden desktop quick-search. Puts the selection into the clipboard. Persists the vault login for the duration of the login session.
Home-page: https://gitlab.com/cspeterson/bw_dmenu
Author: Christopher Peterson
Author-email: contact@cspeterson.net
Project-URL: Documentation, https://gitlab.com/cspeterson/bw_dmenu
Project-URL: Bug Tracker, https://gitlab.com/cspeterson/bw_dmenu/-/issues
Project-URL: Source, https://gitlab.com/cspeterson/bw_dmenu
Classifier: Programming Language :: Python :: 3
Classifier: License :: OSI Approved :: MIT License
Classifier: Operating System :: OS Independent
Requires-Python: >=3.9
License-File: LICENSE
